[
  {
    "id": "z5461d5u-6x32-44hc-4v2a-1f724n241e36",
    "name": "Alphonso Mango(2 Dozen Box)",
    "description": "Our mangoes are brought from the organic orchards at Chitradurga, Karnataka. We and our farmers care for your family and hence our mangoes goes to natural process of ripening.You can also gift mangoes to your loved ones, friends and relatives, Gift wrapping and delivery available.",
    "price": "1545.00",
    "availability": "A",
    "imageUrl": "mango",
    "rating": "4.5"
  },
  {
    "id": "d4138f2c-0z51-17ro-3e9q-4a149j875u33",
    "name": "Chocolate Gift Box",
    "description": "Be it a wedding, a birthday, an anniversary or any other occasion, this is an ideal gift item for your friends and family. This is a round cane basket that is full of Cadbury dairy milk chocolates and cadbury chocolairs gold candies. Order now!",
    "price": "799.00",
    "availability": "O",
    "imageUrl": "choco",
    "rating": "4.1"
  }
]